oberbaum/__init__.py
oberbaum/cli.py
oberbaum/icd_graph.py
oberbaum-0.1.0.dist-info/METADATA
oberbaum-0.1.0.dist-info/WHEEL
oberbaum-0.1.0.dist-info/entry_points.txt
oberbaum-0.1.0.dist-info/RECORD
