Metadata-Version: 2.4
Name: oberbaum
Version: 0.1.0
Summary: A multilingual bridge between ICD-10 versions.
Author-email: Ana Paula Gomes <apgomes88@gmail.com>
Requires-Python: >=3.10
Requires-Dist: dash-cytoscape>=1.0.2
Requires-Dist: dash>=3.0.3
Requires-Dist: networkx>=3.4.2
Requires-Dist: requests>=2.32.3
Requires-Dist: typer>=0.15.2
